telegram_urls_validator/__init__.py
telegram_urls_validator/validator.py
telegram_urls_validator/utils/__init__.py
telegram_urls_validator/utils/exceptions.py
telegram_urls_validator/utils/utils.py
telegram_urls_validator-0.0.2.dist-info/LICENSE
telegram_urls_validator-0.0.2.dist-info/METADATA
telegram_urls_validator-0.0.2.dist-info/WHEEL
telegram_urls_validator-0.0.2.dist-info/top_level.txt
telegram_urls_validator-0.0.2.dist-info/RECORD
