Metadata-Version: 2.1
Name: telegram-urls-validator
Version: 0.0.2
Summary: Validator for Telegram URLs.
Author: Emir Takhaviev
Author-email: tah116emir@outlook.com
Keywords: python,telegram urls,validation
Classifier: Intended Audience :: Developers
Classifier: Programming Language :: Python :: 3
Classifier: Operating System :: Unix
Classifier: Operating System :: MacOS :: MacOS X
Classifier: Operating System :: Microsoft :: Windows
License-File: LICENSE
